hemaherald/__init__.py
hemaherald/main.py
hemaherald/controllers/__init__.py
hemaherald/controllers/timer.py
hemaherald/models/__init__.py
hemaherald/models/timer.py
hemaherald/utils/__init__.py
hemaherald/utils/config.py
hemaherald/views/__init__.py
hemaherald/views/timer.py
hemaherald-0.0.1.dev2.dist-info/METADATA
hemaherald-0.0.1.dev2.dist-info/WHEEL
hemaherald-0.0.1.dev2.dist-info/licenses/LICENSE.txt
hemaherald-0.0.1.dev2.dist-info/RECORD
