Metadata-Version: 2.3
Name: hemaherald
Version: 0.0.1.dev2
Summary: An app for conducting HEMA tournaments (in development)
Project-URL: Repository, https://gitlab.com/dshershukov/hemaherald
Author-email: Danila Shershukov <danila-shershukov@yandex.ru>
Maintainer-email: Danila Shershukov <danila-shershukov@yandex.ru>
License:                     GNU GENERAL PUBLIC LICENSE
License-File: LICENSE.txt
Classifier: Development Status :: 2 - Pre-Alpha
Classifier: Intended Audience :: Developers
Classifier: Intended Audience :: End Users/Desktop
Classifier: License :: OSI Approved :: GNU General Public License v3 or later (GPLv3+)
